Classfile /Users/mayaramamurthy/Documents/School/University/Fourth Year/Term 2/CS 4TB3/Final Project/Source Code/Prototype/HelloWorld.class
  Last modified 29-Mar-2018; size 882 bytes
  MD5 checksum c0e257a4f88110301afcaf9aaceafb9e
  Compiled from "HelloWorld.java"
public class HelloWorld
  minor version: 0
  major version: 52
  flags: ACC_PUBLIC, ACC_SUPER
Constant pool:
   #1 = Methodref          #14.#26        // java/lang/Object."<init>":()V
   #2 = Double             11.1d
   #4 = String             #27            // Hello World
   #5 = Fieldref           #28.#29        // java/lang/System.out:Ljava/io/PrintStream;
   #6 = String             #30            // Hello
   #7 = Methodref          #31.#32        // java/io/PrintStream.println:(Ljava/lang/String;)V
   #8 = String             #33            // It's 5
   #9 = String             #34            // It's not 5
  #10 = String             #35            // It's less than 5
  #11 = String             #36            // While Loop Iterations
  #12 = String             #37            // For loop iteration
  #13 = Class              #38            // HelloWorld
  #14 = Class              #39            // java/lang/Object
  #15 = Utf8               <init>
  #16 = Utf8               ()V
  #17 = Utf8               Code
  #18 = Utf8               LineNumberTable
  #19 = Utf8               main
  #20 = Utf8               ([Ljava/lang/String;)V
  #21 = Utf8               StackMapTable
  #22 = Class              #40            // "[Ljava/lang/String;"
  #23 = Class              #41            // java/lang/String
  #24 = Utf8               SourceFile
  #25 = Utf8               HelloWorld.java
  #26 = NameAndType        #15:#16        // "<init>":()V
  #27 = Utf8               Hello World
  #28 = Class              #42            // java/lang/System
  #29 = NameAndType        #43:#44        // out:Ljava/io/PrintStream;
  #30 = Utf8               Hello
  #31 = Class              #45            // java/io/PrintStream
  #32 = NameAndType        #46:#47        // println:(Ljava/lang/String;)V
  #33 = Utf8               It's 5
  #34 = Utf8               It's not 5
  #35 = Utf8               It's less than 5
  #36 = Utf8               While Loop Iterations
  #37 = Utf8               For loop iteration
  #38 = Utf8               HelloWorld
  #39 = Utf8               java/lang/Object
  #40 = Utf8               [Ljava/lang/String;
  #41 = Utf8               java/lang/String
  #42 = Utf8               java/lang/System
  #43 = Utf8               out
  #44 = Utf8               Ljava/io/PrintStream;
  #45 = Utf8               java/io/PrintStream
  #46 = Utf8               println
  #47 = Utf8               (Ljava/lang/String;)V
{
  public HelloWorld();
    descriptor: ()V
    flags: ACC_PUBLIC
    Code:
      stack=1, locals=1, args_size=1
         0: aload_0
         1: invokespecial #1                  // Method java/lang/Object."<init>":()V
         4: return
      LineNumberTable:
        line 1: 0

  public static void main(java.lang.String[]);
    descriptor: ([Ljava/lang/String;)V
    flags: ACC_PUBLIC, ACC_STATIC
    Code:
      stack=2, locals=7, args_size=1
         0: iconst_5
         1: istore_1
         2: ldc2_w        #2                  // double 11.1d
         5: dstore_2
         6: iconst_1
         7: istore        4
         9: ldc           #4                  // String Hello World
        11: astore        5
        13: getstatic     #5                  // Field java/lang/System.out:Ljava/io/PrintStream;
        16: ldc           #6                  // String Hello
        18: invokevirtual #7                  // Method java/io/PrintStream.println:(Ljava/lang/String;)V
        21: iload_1
        22: iconst_5
        23: if_icmpne     37
        26: getstatic     #5                  // Field java/lang/System.out:Ljava/io/PrintStream;
        29: ldc           #8                  // String It's 5
        31: invokevirtual #7                  // Method java/io/PrintStream.println:(Ljava/lang/String;)V
        34: goto          45
        37: getstatic     #5                  // Field java/lang/System.out:Ljava/io/PrintStream;
        40: ldc           #9                  // String It's not 5
        42: invokevirtual #7                  // Method java/io/PrintStream.println:(Ljava/lang/String;)V
        45: iload_1
        46: iconst_5
        47: if_icmpgt     61
        50: getstatic     #5                  // Field java/lang/System.out:Ljava/io/PrintStream;
        53: ldc           #10                 // String It's less than 5
        55: invokevirtual #7                  // Method java/io/PrintStream.println:(Ljava/lang/String;)V
        58: goto          69
        61: getstatic     #5                  // Field java/lang/System.out:Ljava/io/PrintStream;
        64: ldc           #9                  // String It's not 5
        66: invokevirtual #7                  // Method java/io/PrintStream.println:(Ljava/lang/String;)V
        69: iload_1
        70: iconst_5
        71: if_icmplt     85
        74: getstatic     #5                  // Field java/lang/System.out:Ljava/io/PrintStream;
        77: ldc           #10                 // String It's less than 5
        79: invokevirtual #7                  // Method java/io/PrintStream.println:(Ljava/lang/String;)V
        82: goto          93
        85: getstatic     #5                  // Field java/lang/System.out:Ljava/io/PrintStream;
        88: ldc           #9                  // String It's not 5
        90: invokevirtual #7                  // Method java/io/PrintStream.println:(Ljava/lang/String;)V
        93: iload_1
        94: iconst_5
        95: if_icmple     109
        98: getstatic     #5                  // Field java/lang/System.out:Ljava/io/PrintStream;
       101: ldc           #10                 // String It's less than 5
       103: invokevirtual #7                  // Method java/io/PrintStream.println:(Ljava/lang/String;)V
       106: goto          117
       109: getstatic     #5                  // Field java/lang/System.out:Ljava/io/PrintStream;
       112: ldc           #9                  // String It's not 5
       114: invokevirtual #7                  // Method java/io/PrintStream.println:(Ljava/lang/String;)V
       117: iload         4
       119: iconst_1
       120: if_icmpne     134
       123: getstatic     #5                  // Field java/lang/System.out:Ljava/io/PrintStream;
       126: ldc           #11                 // String While Loop Iterations
       128: invokevirtual #7                  // Method java/io/PrintStream.println:(Ljava/lang/String;)V
       131: goto          117
       134: iconst_0
       135: istore        6
       137: iload         6
       139: bipush        10
       141: if_icmpge     158
       144: getstatic     #5                  // Field java/lang/System.out:Ljava/io/PrintStream;
       147: ldc           #12                 // String For loop iteration
       149: invokevirtual #7                  // Method java/io/PrintStream.println:(Ljava/lang/String;)V
       152: iinc          6, 1
       155: goto          137
       158: return
      LineNumberTable:
        line 4: 0
        line 5: 2
        line 6: 6
        line 7: 9
        line 8: 13
        line 10: 21
        line 11: 26
        line 14: 37
        line 16: 45
        line 17: 50
        line 20: 61
        line 23: 69
        line 24: 74
        line 27: 85
        line 30: 93
        line 31: 98
        line 34: 109
        line 37: 117
        line 38: 123
        line 41: 134
        line 42: 144
        line 41: 152
        line 44: 158
      StackMapTable: number_of_entries = 11
        frame_type = 255 /* full_frame */
          offset_delta = 37
          locals = [ class "[Ljava/lang/String;", int, double, int, class java/lang/String ]
          stack = []
        frame_type = 7 /* same */
        frame_type = 15 /* same */
        frame_type = 7 /* same */
        frame_type = 15 /* same */
        frame_type = 7 /* same */
        frame_type = 15 /* same */
        frame_type = 7 /* same */
        frame_type = 16 /* same */
        frame_type = 252 /* append */
          offset_delta = 2
          locals = [ int ]
        frame_type = 250 /* chop */
          offset_delta = 20
}
SourceFile: "HelloWorld.java"
